<?xml version="1.0" encoding="UTF-8"?>
<are:Ares_odpovedi xmlns:are="http://wwwinfo.mfcr.cz/ares/xml_doc/schemas/ares/ares_answer_vreo/v_1.0.0" 
odpoved_datum_cas="2017-12-11T17:48:04"
odpoved_pocet="1" odpoved_typ="Vypis_VREO" vystup_format="XML" xslt="klient" validation_XSLT="http://wwwinfo.mfcr.cz/ares/xml_doc/schemas/ares/ares_odpovedi.xsl" xmlns:xsi="http://www.w3.org/2001/XMLSchema-instance" xsi:schemaLocation="http://wwwinfo.mfcr.cz/ares/xml_doc/schemas/ares/ares_answer_vreo/v_1.0.0 ../ares_answer_vreo.xsd" Id="aresds">
<are:Odpoved>
 <are:Pomocne_ID>0</are:Pomocne_ID>
 <are:Vysledek_hledani>
  <are:Kod>1</are:Kod>
 </are:Vysledek_hledani>
 <are:Pocet_zaznamu>1</are:Pocet_zaznamu>
 <are:Vypis_VREO>
  <are:Uvod>
   <are:Nadpis>Výpis z veřejného rejstříku v ARES - elektronický opis</are:Nadpis>
   <are:Aktualizace_DB>2017-12-09</are:Aktualizace_DB>
   <are:Datum_vypisu>2017-12-11</are:Datum_vypisu>
   <are:Cas_vypisu>17:48:04</are:Cas_vypisu>
   <are:Typ_vypisu>aktualni</are:Typ_vypisu>
  </are:Uvod>
  <are:Zakladni_udaje>
   <are:Rejstrik>OR</are:Rejstrik>
   <are:ICO>00081370</are:ICO>
   <are:ObchodniFirma>Restaurace Ústí nad Labem - státní podnik &quot;v likvidaci&quot;</are:ObchodniFirma>
   <are:Sidlo>
    <are:ruianKod>17824681</are:ruianKod>
    <are:stat>203</are:stat>
    <are:psc>40021</are:psc>
    <are:okres>Ústí nad Labem</are:okres>
    <are:obec>Ústí nad Labem</are:obec>
    <are:ulice>Pařížská</are:ulice>
    <are:cisloTxt>20</are:cisloTxt>
   </are:Sidlo>
   <are:DatumZapisu>1989-01-01</are:DatumZapisu>
   <are:DatumVymazu>1997-10-31</are:DatumVymazu>
   <are:Cinnosti>
    <are:PredmetPodnikani>
     <are:Text>
Posláním státního podniku a jeho základním předmětem činnosti je
poskytování služeb veřejného stravování a ubytovacích služeb
včetně doplňkových prodejů, služeb a poskytování závodního
stravování v zařízeních restauračního stravování. Za tím účelem
státní podnik provádí:
- výrobu a prodej jídel, nápojů, polotovarů a doplňkového
  sortimentu v provozních jednotkách a odbytových střediscích
  veřejného stravování
- poskytování přechodného ubytování a služeb souvisejících
  v provozovnách k tomu určených, včetně směnárenské činnosti
- poskytování placených i neplacených ostatních služeb v
  souvislosti se službami veřejného stravování a přechodného
  ubytování
- výrobu, rozvoz a prodej výrobků z centrálních výroben
- provozování vnitropodnikové údržby, dopravy a aranžérské
  činnosti
- velkoobchodní činnost v rozsahu potřebném pro zásobování
  svých provozních jednotek
     </are:Text>
     <are:Text>
V souladu s obecně platnými právními předpisy je státní podnik
oprávněn stanovený předmět činnosti překročit i jiným podnikáním
a hospodářskou činností, pokud tím nenaruší plnění jmenovitých
úkolů státního plánu a uzavřené hospodářské závazky.
     </are:Text>
     <are:Text>
Podnik je oprávněn po celém území ČSR provozovat služby cestovní
kanceláře. Za tím účelem je organizace oprávněna poskytovat
hlavní a doplňkové služby domácího a zahraničního cestovního
ruchu.
     </are:Text>
     <are:Text>
Poskytovat průvodcovské služby je organizace oprávněna pouze
prostřednictvím průvodců, majících k této činnosti oprávnění
udělené MOCR ČSR a MOCR SSR.
     </are:Text>
     <are:Text>
Poskytovat služby zahraničního cestovního ruchu je organizace
oprávněna jen na základě a za podmínek povolení k provádění
zahraničně obchodní činnosti. Vzhledem k tomu, že organizace
nemá oprávnění k této činnosti, tato činnost se nezapisuje do
podnikového rejstříku.
     </are:Text>
     <are:Text>
poskytování, zprostředkování a organizování hlavních a
vedlejších služeb cestovního ruchu zahraničním osobám v ČSFR
     </are:Text>
     <are:Text>
poskytování, zprostředkování a organizování hlavních a
vedlejších služeb cestovního ruchu v zahraničí
     </are:Text>
     <are:Text>
provádění obchodní činnosti v rámci hospodářské činnosti a
poskytování služeb
     </are:Text>
     <are:Text>
provádění zábavní činnosti v rámci hospodářské činnosti a
poskytování služeb
     </are:Text>
    </are:PredmetPodnikani>
   </are:Cinnosti>
  </are:Zakladni_udaje>
  <are:Statutarni_organ dza="1989-01-01" dvy="1997-10-31">
   <are:Nazev>Statutární orgán</are:Nazev>
   <are:ZpusobJednani dza="1989-07-25" dvy="1997-10-31">
    <are:Text>
K názvu státního podniku připojí svůj podpis ředitel nebo jeho
statutární zástupce.
    </are:Text>
   </are:ZpusobJednani>
   <are:Clen dza="1989-01-01" dvy="1989-07-19">
    <are:funkce>
     <are:nazev>Pověřen řízením podniku</are:nazev>
    </are:funkce>
    <are:fosoba>
     <are:adresa>
      <are:ruianKod>17837251</are:ruianKod>
      <are:stat>203</are:stat>
      <are:okres>Ústí nad Labem</are:okres>
      <are:obec>Ústí nad Labem</are:obec>
      <are:ulice>Velká Hradební</are:ulice>
      <are:cisloTxt>2318</are:cisloTxt>
     </are:adresa>
     <are:jmeno>Radislav</are:jmeno>
     <are:prijmeni>Smutný</are:prijmeni>
     <are:titulPred>Ing.</are:titulPred>
    </are:fosoba>
   </are:Clen>
   <are:Clen dza="1989-07-19" dvy="1989-11-02">
    <are:funkce>
     <are:nazev>Pracovnice pověřená řízením podniku</are:nazev>
    </are:funkce>
    <are:fosoba>
     <are:adresa>
      <are:ruianKod>3</are:ruianKod>
      <are:stat>203</are:stat>
      <are:okres>Ústí nad Labem</are:okres>
      <are:obec>Ústí nad Labem</are:obec>
      <are:ulice>ČSLA</are:ulice>
      <are:cisloTxt>2903/17</are:cisloTxt>
     </are:adresa>
     <are:jmeno>Jaroslava</are:jmeno>
     <are:prijmeni>Kratochvílová</are:prijmeni>
     <are:titulPred>Ing.</are:titulPred>
    </are:fosoba>
   </are:Clen>
   <are:Clen dza="1989-11-02" dvy="1990-02-02">
    <are:funkce>
     <are:nazev>Pracovník pověřený řízením podniku</are:nazev>
    </are:funkce>
    <are:fosoba>
     <are:adresa>
      <are:ruianKod>3</are:ruianKod>
      <are:stat>203</are:stat>
      <are:okres>Ústí nad Labem</are:okres>
      <are:obec>Ústí nad Labem</are:obec>
      <are:ulice>8.března</are:ulice>
      <are:cisloTxt>626/5</are:cisloTxt>
     </are:adresa>
     <are:jmeno>Jiří</are:jmeno>
     <are:prijmeni>Vyskočil</are:prijmeni>
    </are:fosoba>
   </are:Clen>
   <are:Clen dza="1989-11-10" dvy="1990-04-11">
    <are:funkce>
     <are:nazev>Zástupce ředitele</are:nazev>
    </are:funkce>
    <are:fosoba>
     <are:adresa>
      <are:ruianKod>3</are:ruianKod>
      <are:stat>203</are:stat>
      <are:okres>Ústí nad Labem</are:okres>
      <are:obec>Ústí nad Labem</are:obec>
      <are:ulice>ČSLA</are:ulice>
      <are:cisloTxt>2903/17</are:cisloTxt>
     </are:adresa>
     <are:jmeno>Jaroslava</are:jmeno>
     <are:prijmeni>Kratochvílová</are:prijmeni>
     <are:titulPred>Ing.</are:titulPred>
    </are:fosoba>
   </are:Clen>
   <are:Clen dza="1990-02-02" dvy="1997-10-31">
    <are:funkce>
     <are:nazev>Ředitel státního podniku</are:nazev>
    </are:funkce>
    <are:fosoba>
     <are:adresa>
      <are:ruianKod>3</are:ruianKod>
      <are:stat>203</are:stat>
      <are:okres>Ústí nad Labem</are:okres>
      <are:obec>Ústí nad Labem</are:obec>
      <are:ulice>Pohraniční stráže</are:ulice>
      <are:cisloTxt>2956/4</are:cisloTxt>
     </are:adresa>
     <are:jmeno>Miroslav</are:jmeno>
     <are:prijmeni>Červenka</are:prijmeni>
     <are:titulPred>Ing.</are:titulPred>
    </are:fosoba>
   </are:Clen>
   <are:Clen dza="1990-04-11" dvy="1997-10-31">
    <are:funkce>
     <are:nazev>Statutární zástupce</are:nazev>
    </are:funkce>
    <are:fosoba>
     <are:adresa>
      <are:ruianKod>1</are:ruianKod>
      <are:stat>203</are:stat>
      <are:obec>Ústí nad Labem 1</are:obec>
      <are:ulice>Hostovická</are:ulice>
      <are:cisloTxt>2887/51</are:cisloTxt>
     </are:adresa>
     <are:jmeno>Petr</are:jmeno>
     <are:prijmeni>Deimling</are:prijmeni>
     <are:titulZa>prov.techn.náměstek</are:titulZa>
    </are:fosoba>
   </are:Clen>
   <are:Clen dza="1991-09-26" dvy="1991-10-14">
    <are:funkce>
     <are:nazev>Likvidátor</are:nazev>
    </are:funkce>
    <are:fosoba>
     <are:adresa>
      <are:ruianKod>3</are:ruianKod>
      <are:stat>203</are:stat>
      <are:okres>Ústí nad Labem</are:okres>
      <are:obec>Ústí nad Labem</are:obec>
      <are:ulice>Pohraniční stráže</are:ulice>
      <are:cisloTxt>2956/4</are:cisloTxt>
     </are:adresa>
     <are:jmeno>Miroslav</are:jmeno>
     <are:prijmeni>Červenka</are:prijmeni>
     <are:titulPred>Ing.</are:titulPred>
    </are:fosoba>
   </are:Clen>
   <are:Clen dza="1991-10-14" dvy="1997-10-31">
    <are:funkce>
     <are:nazev>Likvidátor</are:nazev>
    </are:funkce>
    <are:fosoba>
     <are:adresa>
      <are:ruianKod>17896380</are:ruianKod>
      <are:stat>203</are:stat>
      <are:okres>Ústí nad Labem</are:okres>
      <are:obec>Ústí nad Labem</are:obec>
      <are:ulice>Neštěmická</are:ulice>
      <are:cisloTxt>688/1</are:cisloTxt>
     </are:adresa>
     <are:jmeno>Jaroslav</are:jmeno>
     <are:prijmeni>Stinka</are:prijmeni>
    </are:fosoba>
   </are:Clen>
  </are:Statutarni_organ>
 </are:Vypis_VREO>
</are:Odpoved>
</are:Ares_odpovedi>
