<?xml version="1.0" encoding="UTF-8"?>
<are:Ares_odpovedi xmlns:are="http://wwwinfo.mfcr.cz/ares/xml_doc/schemas/ares/ares_answer_vreo/v_1.0.0" 
odpoved_datum_cas="2018-11-06T18:33:52"
odpoved_pocet="1" odpoved_typ="Vypis_VREO" vystup_format="XML" xslt="klient" validation_XSLT="http://wwwinfo.mfcr.cz/ares/xml_doc/schemas/ares/ares_odpovedi.xsl" xmlns:xsi="http://www.w3.org/2001/XMLSchema-instance" xsi:schemaLocation="http://wwwinfo.mfcr.cz/ares/xml_doc/schemas/ares/ares_answer_vreo/v_1.0.0 ../ares_answer_vreo.xsd" Id="aresds">
<are:Odpoved>
 <are:Pomocne_ID>0</are:Pomocne_ID>
 <are:Vysledek_hledani>
  <are:Kod>1</are:Kod>
 </are:Vysledek_hledani>
 <are:Pocet_zaznamu>1</are:Pocet_zaznamu>
 <are:Vypis_VREO>
  <are:Uvod>
   <are:Nadpis>Výpis z veřejného rejstříku v ARES - elektronický opis</are:Nadpis>
   <are:Aktualizace_DB>2018-11-06</are:Aktualizace_DB>
   <are:Datum_vypisu>2018-11-06</are:Datum_vypisu>
   <are:Cas_vypisu>18:33:52</are:Cas_vypisu>
   <are:Typ_vypisu>aktualni</are:Typ_vypisu>
  </are:Uvod>
  <are:Zakladni_udaje>
   <are:Rejstrik>OR</are:Rejstrik>
   <are:ICO>00201073</are:ICO>
   <are:ObchodniFirma>CORAX akciová společnost  (Company by shares - anglicky, Aktiengesselschaft A.G. - německy, Société Anonyme S.A. - francouzsky &quot;v likvidaci&quot;</are:ObchodniFirma>
   <are:Sidlo>
    <are:ruianKod>26182220</are:ruianKod>
    <are:stat>203</are:stat>
    <are:psc>19000</are:psc>
    <are:obec>Praha 9</are:obec>
    <are:ulice>Českomoravská</are:ulice>
    <are:cisloTxt>21</are:cisloTxt>
   </are:Sidlo>
   <are:DatumZapisu>1990-11-27</are:DatumZapisu>
   <are:DatumVymazu>2002-08-29</are:DatumVymazu>
   <are:Cinnosti>
    <are:PredmetPodnikani>
     <are:Text>
koupě zboží za účelem jeho dalšího prodeje a prodej
     </are:Text>
     <are:Text>
průzkum trhu - marketing
     </are:Text>
     <are:Text>
poradenství v obchodní činnosti
     </are:Text>
    </are:PredmetPodnikani>
   </are:Cinnosti>
  </are:Zakladni_udaje>
  <are:Statutarni_organ dza="1990-11-27" dvy="2002-08-29">
   <are:Nazev>Statutární orgán - představenstvo</are:Nazev>
   <are:ZpusobJednani dza="1990-11-27" dvy="1991-07-11">
    <are:Text>
Podepisování za společnost:
Děje se tak, že k vytištěnému nebo napsanému názvu společnosti
připojí svůj podpis:
- všichni členové představenstva nebo na základě zmocnění jeho
jednotliví členové nebo
- prokuristé a další zplnomocnění pracovníci v rozsahu udělené
plné moci nebo
- jiní pracovníci v rozsahu dispozic daných organizačním a pod-
pisovým řádem společnosti k plnění pracovních úkolů.
    </are:Text>
   </are:ZpusobJednani>
   <are:ZpusobJednani dza="1991-07-11" dvy="1993-03-23">
    <are:Text>
Podepisování za společnost:
Děje se tak, že k napsanému nebo vytištěnému názvu společ-
nosti připojí svůj podpis:
- všichni členové představenstva nebo na základě zmocnění
jeho jednotliví členové nebo výkonný ředitel společnosti
- prokuristé a další zplnomocnění pracovníci v rozsahu udě-
lené plné moci nebo
- jiní pracovníci v rozsahu dispozic daných organizačním a
podpisovým řádem společnosti k plnění pracovních úkolů na
základě písemné moci výkonného ředitele.
    </are:Text>
   </are:ZpusobJednani>
   <are:ZpusobJednani dza="1993-03-23" dvy="2002-08-29">
    <are:Text>
Způsob jednání jménem společnosti:
Navenek jedná za společnost představenstvo a to každý
z členů samostatně.
Podepisování za společnost se děje tak, že k vytištěnému
nebo jinak vyznačenému obchodnímu názvu společnosti připojí
svůj podpis samostatně jeden z členů představenstva.
    </are:Text>
   </are:ZpusobJednani>
   <are:Clen dza="1990-11-27" dvy="1991-07-11">
    <are:funkce>
     <are:nazev>člen představenstva</are:nazev>
    </are:funkce>
    <are:fosoba>
     <are:adresa>
      <are:ruianKod>22635335</are:ruianKod>
      <are:stat>203</are:stat>
      <are:psc>10000</are:psc>
      <are:obec>Praha 10</are:obec>
      <are:ulice>Nad kapličkou</are:ulice>
      <are:cisloTxt>14</are:cisloTxt>
     </are:adresa>
     <are:jmeno>Josef</are:jmeno>
     <are:prijmeni>Piga</are:prijmeni>
     <are:titulPred>ing.</are:titulPred>
    </are:fosoba>
   </are:Clen>
   <are:Clen dza="1990-11-27" dvy="1993-03-23">
    <are:funkce>
     <are:nazev>předseda představenstva</are:nazev>
    </are:funkce>
    <are:fosoba>
     <are:adresa>
      <are:ruianKod>3</are:ruianKod>
      <are:stat>203</are:stat>
      <are:psc>14100</are:psc>
      <are:obec>Praha 4</are:obec>
      <are:ulice>Bělčické</are:ulice>
      <are:cisloTxt>2148/15</are:cisloTxt>
     </are:adresa>
     <are:jmeno>Ludvík</are:jmeno>
     <are:prijmeni>Skočdopole</are:prijmeni>
     <are:titulPred>ing.</are:titulPred>
    </are:fosoba>
   </are:Clen>
   <are:Clen dza="1990-11-27" dvy="1993-03-23">
    <are:funkce>
     <are:nazev>člen představenstva</are:nazev>
    </are:funkce>
    <are:fosoba>
     <are:adresa>
      <are:ruianKod>4</are:ruianKod>
      <are:stat>203</are:stat>
      <are:psc>14700</are:psc>
      <are:obec>Praha 4</are:obec>
      <are:ulice>V malých domech</are:ulice>
      <are:cisloTxt>III/1555</are:cisloTxt>
     </are:adresa>
     <are:jmeno>František</are:jmeno>
     <are:prijmeni>Háva</are:prijmeni>
     <are:titulPred>ing.</are:titulPred>
    </are:fosoba>
   </are:Clen>
   <are:Clen dza="1991-07-11" dvy="1993-03-23">
    <are:funkce>
     <are:nazev>výkonný ředitel,představenstvo</are:nazev>
    </are:funkce>
    <are:fosoba>
     <are:adresa>
      <are:ruianKod>21793816</are:ruianKod>
      <are:stat>203</are:stat>
      <are:psc>13000</are:psc>
      <are:obec>Praha 3</are:obec>
      <are:ulice>Malešická</are:ulice>
      <are:cisloTxt>33</are:cisloTxt>
     </are:adresa>
     <are:jmeno>Jiří</are:jmeno>
     <are:prijmeni>Terek</are:prijmeni>
     <are:titulPred>JUDr.</are:titulPred>
    </are:fosoba>
   </are:Clen>
   <are:Clen dza="1993-03-23" dvy="2002-08-29">
    <are:funkce>
     <are:nazev>předseda představenstva</are:nazev>
    </are:funkce>
    <are:fosoba>
     <are:adresa>
      <are:ruianKod>3</are:ruianKod>
      <are:stat>203</are:stat>
      <are:obec>Liberec</are:obec>
      <are:ulice>Soukenné nám.</are:ulice>
      <are:cisloTxt>26/2</are:cisloTxt>
     </are:adresa>
     <are:jmeno>Petr</are:jmeno>
     <are:prijmeni>Pernička</are:prijmeni>
    </are:fosoba>
   </are:Clen>
   <are:Clen dza="1993-03-23" dvy="2002-08-29">
    <are:funkce>
     <are:nazev>výkonný ředitel</are:nazev>
    </are:funkce>
    <are:fosoba>
     <are:adresa>
      <are:ruianKod>23762756</are:ruianKod>
      <are:stat>203</are:stat>
      <are:obec>Liberec</are:obec>
      <are:ulice>Kostelní</are:ulice>
      <are:cisloTxt>3/11</are:cisloTxt>
     </are:adresa>
     <are:jmeno>Jan</are:jmeno>
     <are:prijmeni>Moravec</are:prijmeni>
    </are:fosoba>
   </are:Clen>
   <are:Clen dza="1993-03-23" dvy="2002-08-29">
    <are:funkce>
     <are:nazev>člen představenstva</are:nazev>
    </are:funkce>
    <are:fosoba>
     <are:adresa>
      <are:ruianKod>3</are:ruianKod>
      <are:stat>203</are:stat>
      <are:obec>Liberec</are:obec>
      <are:ulice>Soukenné nám.</are:ulice>
      <are:cisloTxt>26/2</are:cisloTxt>
     </are:adresa>
     <are:jmeno>Dana</are:jmeno>
     <are:prijmeni>Perničková</are:prijmeni>
    </are:fosoba>
   </are:Clen>
  </are:Statutarni_organ>
  <are:Statutarni_organ dza="2002-02-06" dvy="2002-08-29">
   <are:Nazev>Likvidátor</are:Nazev>
   <are:Clen dza="2002-02-06" dvy="2002-08-29">
    <are:fosoba>
     <are:adresa>
      <are:ruianKod>19561105</are:ruianKod>
      <are:stat>203</are:stat>
      <are:okres>Brno-město</are:okres>
      <are:obec>Brno</are:obec>
      <are:ulice>U Hřiště</are:ulice>
      <are:cisloTxt>229/9</are:cisloTxt>
     </are:adresa>
     <are:jmeno>Josef</are:jmeno>
     <are:prijmeni>Macků</are:prijmeni>
     <are:titulPred>ing.</are:titulPred>
    </are:fosoba>
   </are:Clen>
  </are:Statutarni_organ>
  <are:Jiny_organ dza="1993-03-23" dvy="2002-08-29">
   <are:Nazev>Dozorčí rada</are:Nazev>
   <are:Clen dza="1993-03-23" dvy="2002-08-29">
    <are:funkce>
     <are:nazev>předseda</are:nazev>
    </are:funkce>
    <are:fosoba>
     <are:adresa>
      <are:ruianKod>100</are:ruianKod>
      <are:stat>203</are:stat>
      <are:obec>Brno</are:obec>
      <are:ulice>Ponava 12c</are:ulice>
     </are:adresa>
     <are:jmeno>Pavel</are:jmeno>
     <are:prijmeni>Pernička</are:prijmeni>
     <are:titulPred>MUDr.</are:titulPred>
    </are:fosoba>
   </are:Clen>
   <are:Clen dza="1993-03-23" dvy="2002-08-29">
    <are:fosoba>
     <are:adresa>
      <are:ruianKod>23777869</are:ruianKod>
      <are:stat>203</are:stat>
      <are:obec>Liberec</are:obec>
      <are:ulice>Kominická</are:ulice>
      <are:cisloTxt>600</are:cisloTxt>
     </are:adresa>
     <are:jmeno>Stanislava</are:jmeno>
     <are:prijmeni>Chýlová</are:prijmeni>
    </are:fosoba>
   </are:Clen>
   <are:Clen dza="1993-03-23" dvy="2002-08-29">
    <are:fosoba>
     <are:adresa>
      <are:ruianKod>23772816</are:ruianKod>
      <are:stat>203</are:stat>
      <are:obec>Liberec</are:obec>
      <are:ulice>Slovenská</are:ulice>
      <are:cisloTxt>724/14</are:cisloTxt>
     </are:adresa>
     <are:jmeno>Michail</are:jmeno>
     <are:prijmeni>Šiškin</are:prijmeni>
    </are:fosoba>
   </are:Clen>
  </are:Jiny_organ>
 </are:Vypis_VREO>
</are:Odpoved>
</are:Ares_odpovedi>
