<?xml version="1.0" encoding="UTF-8"?>
<are:Ares_odpovedi xmlns:are="http://wwwinfo.mfcr.cz/ares/xml_doc/schemas/ares/ares_answer_vreo/v_1.0.0" 
odpoved_datum_cas="2018-11-09T16:03:07"
odpoved_pocet="1" odpoved_typ="Vypis_VREO" vystup_format="XML" xslt="klient" validation_XSLT="http://wwwinfo.mfcr.cz/ares/xml_doc/schemas/ares/ares_odpovedi.xsl" xmlns:xsi="http://www.w3.org/2001/XMLSchema-instance" xsi:schemaLocation="http://wwwinfo.mfcr.cz/ares/xml_doc/schemas/ares/ares_answer_vreo/v_1.0.0 ../ares_answer_vreo.xsd" Id="aresds">
<are:Odpoved>
 <are:Pomocne_ID>0</are:Pomocne_ID>
 <are:Vysledek_hledani>
  <are:Kod>1</are:Kod>
 </are:Vysledek_hledani>
 <are:Pocet_zaznamu>1</are:Pocet_zaznamu>
 <are:Vypis_VREO>
  <are:Uvod>
   <are:Nadpis>Výpis z veřejného rejstříku v ARES - elektronický opis</are:Nadpis>
   <are:Aktualizace_DB>2018-11-09</are:Aktualizace_DB>
   <are:Datum_vypisu>2018-11-09</are:Datum_vypisu>
   <are:Cas_vypisu>16:03:07</are:Cas_vypisu>
   <are:Typ_vypisu>aktualni</are:Typ_vypisu>
  </are:Uvod>
  <are:Zakladni_udaje>
   <are:Rejstrik>ROPS</are:Rejstrik>
   <are:ICO>25731289</are:ICO>
   <are:ObchodniFirma>Československé dokumentační středisko, o.p.s.</are:ObchodniFirma>
   <are:Sidlo>
    <are:ruianKod>27931901</are:ruianKod>
    <are:stat>203</are:stat>
    <are:psc>11000</are:psc>
    <are:okres>Hlavní město Praha</are:okres>
    <are:obec>Praha</are:obec>
    <are:castObce>Vinohrady</are:castObce>
    <are:mop>Praha 1</are:mop>
    <are:ulice>Vinohradská</are:ulice>
    <are:cisloPop>52</are:cisloPop>
    <are:cisloOr>1</are:cisloOr>
   </are:Sidlo>
   <are:DatumZapisu>1999-01-26</are:DatumZapisu>
   <are:Cinnosti>
    <are:PredmetPodnikani>
     <are:Text>
informační, publikační a osvětová činnost, výzkum a dokumentace
dějin domácího a exilového antitotalitního odporu v
Československu v letech 1948 - 1989, zejména:
     </are:Text>
     <are:Text>
a) provozování nevládního badatelského, dokumentačního a
studijního střediska pro dějiny domácího a exilového
antitotalitního odporu,
     </are:Text>
     <are:Text>
b) shoramažďování pramenného materiálu, osobních svědectví a
dokumentace z domácích i zahraničních zdrojů, archivování a
zpřístupnění pro potřeby široké veřejnosti a pro výzkum ze
strany domácích i zahraničních vědců
     </are:Text>
     <are:Text>
c) udržování a provozování specializované knihovny
     </are:Text>
     <are:Text>
d) vydávání specializovaných periodik a vlastních publikací,
nejedná se o činnost dle par.2 zák.č. 455/91 Sb.
     </are:Text>
     <are:Text>
e) přispívání ke celospolečenské diskusi o historii komunistické
éry v Československu
     </are:Text>
     <are:Text>
f) podpora mezinárodních srovnávacích studií zaměřených na
problematiku nezáviského myšlení, samizdatové literatury,
formování zárodků občanské společnosti a občanských aktivit v
rámci totalitního systému
     </are:Text>
    </are:PredmetPodnikani>
    <are:DoplnkovaCinnost>
     <are:Text>
neprovozována
     </are:Text>
    </are:DoplnkovaCinnost>
   </are:Cinnosti>
  </are:Zakladni_udaje>
  <are:Jiny_organ dza="1999-01-26">
   <are:Nazev>Dozorčí rada</are:Nazev>
   <are:Clen dza="2010-06-08">
    <are:clenstvi>
     <are:vznikClenstvi>2009-04-29</are:vznikClenstvi>
    </are:clenstvi>
    <are:funkce>
     <are:nazev>předseda dozorčí rady</are:nazev>
     <are:vznikFunkce>2010-04-21</are:vznikFunkce>
    </are:funkce>
    <are:fosoba>
     <are:adresa>
      <are:ruianKod>22028781</are:ruianKod>
      <are:stat>203</are:stat>
      <are:psc>15000</are:psc>
      <are:obec>Praha 5</are:obec>
      <are:castObce>Košíře</are:castObce>
      <are:ulice>Štěpánkova</are:ulice>
      <are:cisloPop>1014</are:cisloPop>
      <are:cisloOr>4a</are:cisloOr>
     </are:adresa>
     <are:jmeno>Vojtěch</are:jmeno>
     <are:prijmeni>Čelko</are:prijmeni>
     <are:titulPred>PhDr.</are:titulPred>
    </are:fosoba>
   </are:Clen>
   <are:Clen dza="2013-09-13">
    <are:clenstvi>
     <are:vznikClenstvi>2009-04-29</are:vznikClenstvi>
    </are:clenstvi>
    <are:funkce>
     <are:nazev>člen dozorčí rady</are:nazev>
    </are:funkce>
    <are:fosoba>
     <are:adresa>
      <are:ruianKod>8617066</are:ruianKod>
      <are:stat>203</are:stat>
      <are:psc>27024</are:psc>
      <are:obec>Sýkořice</are:obec>
      <are:castObce>Sýkořice</are:castObce>
      <are:cisloPop>83</are:cisloPop>
     </are:adresa>
     <are:jmeno>KAREL</are:jmeno>
     <are:prijmeni>SCHWARZENBERG</are:prijmeni>
    </are:fosoba>
   </are:Clen>
   <are:Clen dza="2016-10-05">
    <are:clenstvi>
     <are:vznikClenstvi>2016-04-21</are:vznikClenstvi>
    </are:clenstvi>
    <are:funkce>
     <are:nazev>člen DR</are:nazev>
     <are:vznikFunkce>2016-04-21</are:vznikFunkce>
    </are:funkce>
    <are:fosoba>
     <are:adresa>
      <are:ruianKod>22728686</are:ruianKod>
      <are:stat>203</are:stat>
      <are:psc>19300</are:psc>
      <are:okres>Hlavní město Praha</are:okres>
      <are:obec>Praha</are:obec>
      <are:castObce>Horní Počernice</are:castObce>
      <are:mop>Praha 9</are:mop>
      <are:ulice>Pavlišovská</are:ulice>
      <are:cisloPop>2295</are:cisloPop>
      <are:cisloOr>8</are:cisloOr>
     </are:adresa>
     <are:jmeno>RADEK</are:jmeno>
     <are:prijmeni>SCHOVÁNEK</are:prijmeni>
    </are:fosoba>
   </are:Clen>
  </are:Jiny_organ>
  <are:Jiny_organ dza="1999-01-26">
   <are:Nazev>Správní rada</are:Nazev>
   <are:Clen dza="2010-02-25">
    <are:clenstvi>
     <are:vznikClenstvi>2009-04-29</are:vznikClenstvi>
    </are:clenstvi>
    <are:funkce>
     <are:nazev>člen správní rady</are:nazev>
    </are:funkce>
    <are:fosoba>
     <are:adresa>
      <are:ruianKod>22292730</are:ruianKod>
      <are:stat>203</are:stat>
      <are:psc>17000</are:psc>
      <are:obec>Praha 7</are:obec>
      <are:castObce>Bubeneč</are:castObce>
      <are:ulice>Nad Královskou oborou</are:ulice>
      <are:cisloTxt>101/3</are:cisloTxt>
     </are:adresa>
     <are:jmeno>Barbara</are:jmeno>
     <are:prijmeni>Day</are:prijmeni>
    </are:fosoba>
   </are:Clen>
   <are:Clen dza="2010-02-25">
    <are:clenstvi>
     <are:vznikClenstvi>2009-04-29</are:vznikClenstvi>
    </are:clenstvi>
    <are:funkce>
     <are:nazev>člen správní rady</are:nazev>
    </are:funkce>
    <are:fosoba>
     <are:adresa>
      <are:ruianKod>22166939</are:ruianKod>
      <are:stat>203</are:stat>
      <are:psc>16900</are:psc>
      <are:obec>Praha 6</are:obec>
      <are:castObce>Břevnov</are:castObce>
      <are:ulice>Kolátorova</are:ulice>
      <are:cisloTxt>1622/10</are:cisloTxt>
     </are:adresa>
     <are:jmeno>Martin</are:jmeno>
     <are:prijmeni>Machovec</are:prijmeni>
     <are:titulPred>PhDr.</are:titulPred>
    </are:fosoba>
   </are:Clen>
   <are:Clen dza="2010-02-25">
    <are:clenstvi>
     <are:vznikClenstvi>2009-04-29</are:vznikClenstvi>
    </are:clenstvi>
    <are:funkce>
     <are:nazev>člen správní rady</are:nazev>
    </are:funkce>
    <are:fosoba>
     <are:adresa>
      <are:ruianKod>17202281</are:ruianKod>
      <are:stat>203</are:stat>
      <are:psc>75661</are:psc>
      <are:okres>Vsetín</are:okres>
      <are:obec>Rožnov pod Radhoštěm</are:obec>
      <are:ulice>5. května</are:ulice>
      <are:cisloTxt>289</are:cisloTxt>
     </are:adresa>
     <are:jmeno>Milan</are:jmeno>
     <are:prijmeni>Drápala</are:prijmeni>
     <are:titulPred>Mgr.</are:titulPred>
    </are:fosoba>
   </are:Clen>
   <are:Clen dza="2010-02-25">
    <are:clenstvi>
     <are:vznikClenstvi>2009-04-29</are:vznikClenstvi>
    </are:clenstvi>
    <are:funkce>
     <are:nazev>člen správní rady</are:nazev>
    </are:funkce>
    <are:fosoba>
     <are:adresa>
      <are:ruianKod>22381279</are:ruianKod>
      <are:stat>203</are:stat>
      <are:psc>18000</are:psc>
      <are:obec>Praha 8</are:obec>
      <are:castObce>Libeň</are:castObce>
      <are:ulice>Braunerova</are:ulice>
      <are:cisloTxt>852/4</are:cisloTxt>
     </are:adresa>
     <are:jmeno>Jiří</are:jmeno>
     <are:prijmeni>Suk</are:prijmeni>
     <are:titulPred>PhDr.</are:titulPred>
     <are:titulZa>PhD.</are:titulZa>
    </are:fosoba>
   </are:Clen>
   <are:Clen dza="2010-06-08">
    <are:clenstvi>
     <are:vznikClenstvi>2010-04-21</are:vznikClenstvi>
    </are:clenstvi>
    <are:funkce>
     <are:nazev>předseda správní rady</are:nazev>
     <are:vznikFunkce>2010-04-21</are:vznikFunkce>
    </are:funkce>
    <are:fosoba>
     <are:adresa>
      <are:ruianKod>22728279</are:ruianKod>
      <are:stat>203</are:stat>
      <are:psc>14200</are:psc>
      <are:obec>Praha 4</are:obec>
      <are:castObce>Libuš</are:castObce>
      <are:ulice>Zbudovská</are:ulice>
      <are:cisloPop>764</are:cisloPop>
      <are:cisloOr>9</are:cisloOr>
     </are:adresa>
     <are:jmeno>Vilém</are:jmeno>
     <are:prijmeni>Prečan</are:prijmeni>
     <are:titulPred>prof. PhDr.</are:titulPred>
    </are:fosoba>
   </are:Clen>
   <are:Clen dza="2010-06-08">
    <are:clenstvi>
     <are:vznikClenstvi>2010-04-21</are:vznikClenstvi>
    </are:clenstvi>
    <are:funkce>
     <are:nazev>člen správní rady</are:nazev>
    </are:funkce>
    <are:fosoba>
     <are:adresa>
      <are:stat>703</are:stat>
      <are:psc>82104</are:psc>
      <are:obec>Bratislava</are:obec>
      <are:ulice>Slowackého</are:ulice>
      <are:cisloTxt>21</are:cisloTxt>
     </are:adresa>
     <are:jmeno>Miroslav</are:jmeno>
     <are:prijmeni>Kusý</are:prijmeni>
     <are:titulPred>prof. PhDr.</are:titulPred>
    </are:fosoba>
   </are:Clen>
   <are:Clen dza="2010-06-08">
    <are:clenstvi>
     <are:vznikClenstvi>2010-04-21</are:vznikClenstvi>
    </are:clenstvi>
    <are:funkce>
     <are:nazev>člen správní rady</are:nazev>
    </are:funkce>
    <are:fosoba>
     <are:adresa>
      <are:ruianKod>22742743</are:ruianKod>
      <are:stat>203</are:stat>
      <are:psc>16200</are:psc>
      <are:obec>Praha 6</are:obec>
      <are:castObce>Veleslavín</are:castObce>
      <are:ulice>Křenova</are:ulice>
      <are:cisloPop>439</are:cisloPop>
      <are:cisloOr>13</are:cisloOr>
     </are:adresa>
     <are:jmeno>Petr</are:jmeno>
     <are:prijmeni>Pithart</are:prijmeni>
     <are:titulPred>doc. JUDr.</are:titulPred>
    </are:fosoba>
   </are:Clen>
   <are:Clen dza="2015-06-25">
    <are:clenstvi>
     <are:vznikClenstvi>2010-04-21</are:vznikClenstvi>
    </are:clenstvi>
    <are:funkce>
     <are:nazev>člen správní rady</are:nazev>
    </are:funkce>
    <are:fosoba>
     <are:adresa>
      <are:ruianKod>22205195</are:ruianKod>
      <are:stat>203</are:stat>
      <are:psc>16000</are:psc>
      <are:okres>Hlavní město Praha</are:okres>
      <are:obec>Praha</are:obec>
      <are:castObce>Dejvice</are:castObce>
      <are:mop>Praha 6</are:mop>
      <are:ulice>Velvarská</are:ulice>
      <are:cisloPop>1700</are:cisloPop>
      <are:cisloOr>27</are:cisloOr>
     </are:adresa>
     <are:jmeno>TOMÁŠ</are:jmeno>
     <are:prijmeni>VRBA</are:prijmeni>
     <are:titulPred>PhDr.</are:titulPred>
    </are:fosoba>
   </are:Clen>
   <are:Clen dza="2015-07-16">
    <are:clenstvi>
     <are:vznikClenstvi>2010-04-21</are:vznikClenstvi>
    </are:clenstvi>
    <are:funkce>
     <are:nazev>člen správní rady</are:nazev>
    </are:funkce>
    <are:fosoba>
     <are:adresa>
      <are:ruianKod>21714649</are:ruianKod>
      <are:stat>203</are:stat>
      <are:psc>11000</are:psc>
      <are:okres>Hlavní město Praha</are:okres>
      <are:obec>Praha</are:obec>
      <are:castObce>Nové Město</are:castObce>
      <are:mop>Praha 1</are:mop>
      <are:ulice>Klimentská</are:ulice>
      <are:cisloPop>2065</are:cisloPop>
      <are:cisloOr>17</are:cisloOr>
     </are:adresa>
     <are:jmeno>JIŘINA</are:jmeno>
     <are:prijmeni>ŠIKLOVÁ</are:prijmeni>
     <are:titulPred>doc. PhDr.</are:titulPred>
     <are:titulZa>CSc.</are:titulZa>
    </are:fosoba>
   </are:Clen>
   <are:Clen dza="2016-08-27">
    <are:clenstvi>
     <are:vznikClenstvi>2009-04-29</are:vznikClenstvi>
    </are:clenstvi>
    <are:funkce>
     <are:nazev>člen správní rady</are:nazev>
    </are:funkce>
    <are:fosoba>
     <are:adresa>
      <are:ruianKod>21755680</are:ruianKod>
      <are:stat>203</are:stat>
      <are:psc>12000</are:psc>
      <are:okres>Hlavní město Praha</are:okres>
      <are:obec>Praha</are:obec>
      <are:castObce>Vinohrady</are:castObce>
      <are:mop>Praha 2</are:mop>
      <are:ulice>Slavíkova</are:ulice>
      <are:cisloPop>1657</are:cisloPop>
      <are:cisloOr>1</are:cisloOr>
     </are:adresa>
     <are:jmeno>JÁN</are:jmeno>
     <are:prijmeni>KULA</are:prijmeni>
     <are:titulPred>Mgr.</are:titulPred>
    </are:fosoba>
   </are:Clen>
   <are:Clen dza="2016-10-05">
    <are:clenstvi>
     <are:vznikClenstvi>2016-04-21</are:vznikClenstvi>
    </are:clenstvi>
    <are:funkce>
     <are:nazev>člen SR</are:nazev>
     <are:vznikFunkce>2016-04-21</are:vznikFunkce>
    </are:funkce>
    <are:fosoba>
     <are:adresa>
      <are:ruianKod>22154752</are:ruianKod>
      <are:stat>203</are:stat>
      <are:psc>16900</are:psc>
      <are:okres>Hlavní město Praha</are:okres>
      <are:obec>Praha</are:obec>
      <are:castObce>Břevnov</are:castObce>
      <are:mop>Praha 6</are:mop>
      <are:ulice>Závěrka</are:ulice>
      <are:cisloPop>654</are:cisloPop>
      <are:cisloOr>9</are:cisloOr>
     </are:adresa>
     <are:jmeno>FRANCIS</are:jmeno>
     <are:prijmeni>RAŠKA</are:prijmeni>
     <are:titulPred>doc. PhDr.</are:titulPred>
     <are:titulZa>PhD</are:titulZa>
    </are:fosoba>
   </are:Clen>
   <are:Clen dza="2016-10-05">
    <are:clenstvi>
     <are:vznikClenstvi>2016-04-21</are:vznikClenstvi>
    </are:clenstvi>
    <are:funkce>
     <are:nazev>člen SR</are:nazev>
     <are:vznikFunkce>2016-04-21</are:vznikFunkce>
    </are:funkce>
    <are:fosoba>
     <are:adresa>
      <are:ruianKod>22106090</are:ruianKod>
      <are:stat>203</are:stat>
      <are:psc>15000</are:psc>
      <are:okres>Hlavní město Praha</are:okres>
      <are:obec>Praha</are:obec>
      <are:castObce>Smíchov</are:castObce>
      <are:mop>Praha 5</are:mop>
      <are:ulice>U dvou srpů</are:ulice>
      <are:cisloPop>2819</are:cisloPop>
      <are:cisloOr>12</are:cisloOr>
     </are:adresa>
     <are:jmeno>MIROSLAV</are:jmeno>
     <are:prijmeni>MICHELA</are:prijmeni>
     <are:titulPred>Mgr.</are:titulPred>
     <are:titulZa>PhD</are:titulZa>
    </are:fosoba>
   </are:Clen>
  </are:Jiny_organ>
  <are:Jiny_organ dza="1999-01-26">
   <are:Nazev>Zakladatel</are:Nazev>
   <are:Clen dza="1999-01-26">
    <are:fosoba>
     <are:adresa>
      <are:stat>203</are:stat>
      <are:psc>15000</are:psc>
      <are:okres>Praha 5</are:okres>
      <are:obec>Praha 5</are:obec>
      <are:ulice>Štěpánkova</are:ulice>
      <are:cisloTxt>6/a</are:cisloTxt>
     </are:adresa>
     <are:jmeno>Vojtěch</are:jmeno>
     <are:prijmeni>Čelko</are:prijmeni>
     <are:titulPred>PhDr.</are:titulPred>
    </are:fosoba>
   </are:Clen>
   <are:Clen dza="1999-01-26">
    <are:fosoba>
     <are:adresa>
      <are:ruianKod>21704856</are:ruianKod>
      <are:stat>203</are:stat>
      <are:psc>11000</are:psc>
      <are:okres>Praha 1</are:okres>
      <are:obec>Praha 1</are:obec>
      <are:ulice>Školská</are:ulice>
      <are:cisloTxt>38</are:cisloTxt>
     </are:adresa>
     <are:jmeno>Václav</are:jmeno>
     <are:prijmeni>Kasík</are:prijmeni>
     <are:titulPred>Ing.</are:titulPred>
    </are:fosoba>
   </are:Clen>
   <are:Clen dza="1999-01-26">
    <are:fosoba>
     <are:adresa>
      <are:ruianKod>22706496</are:ruianKod>
      <are:stat>203</are:stat>
      <are:psc>15200</are:psc>
      <are:okres>Praha 5</are:okres>
      <are:obec>Praha 5</are:obec>
      <are:ulice>Devonská</are:ulice>
      <are:cisloTxt>999/1</are:cisloTxt>
     </are:adresa>
     <are:jmeno>Jiří</are:jmeno>
     <are:prijmeni>Oberfalzer</are:prijmeni>
    </are:fosoba>
   </are:Clen>
   <are:Clen dza="1999-01-26">
    <are:fosoba>
     <are:adresa>
      <are:ruianKod>22728279</are:ruianKod>
      <are:stat>203</are:stat>
      <are:psc>14200</are:psc>
      <are:okres>Praha 4</are:okres>
      <are:obec>Praha 4</are:obec>
      <are:ulice>Zbudovská</are:ulice>
      <are:cisloTxt>764/9</are:cisloTxt>
     </are:adresa>
     <are:jmeno>Vilém</are:jmeno>
     <are:prijmeni>Prečan</are:prijmeni>
     <are:titulPred>Doc.PhDr.</are:titulPred>
    </are:fosoba>
   </are:Clen>
   <are:Clen dza="1999-01-26">
    <are:fosoba>
     <are:adresa>
      <are:ruianKod>22381279</are:ruianKod>
      <are:stat>203</are:stat>
      <are:psc>18000</are:psc>
      <are:okres>Praha 8</are:okres>
      <are:obec>Praha 8</are:obec>
      <are:ulice>Braunerova</are:ulice>
      <are:cisloTxt>4</are:cisloTxt>
     </are:adresa>
     <are:jmeno>Jiří</are:jmeno>
     <are:prijmeni>Suk</are:prijmeni>
     <are:titulPred>Mgr.</are:titulPred>
    </are:fosoba>
   </are:Clen>
   <are:Clen dza="2013-09-13">
    <are:fosoba>
     <are:adresa>
      <are:ruianKod>8617066</are:ruianKod>
      <are:stat>203</are:stat>
      <are:psc>27024</are:psc>
      <are:obec>Sýkořice</are:obec>
      <are:castObce>Sýkořice</are:castObce>
      <are:cisloPop>83</are:cisloPop>
     </are:adresa>
     <are:jmeno>KAREL</are:jmeno>
     <are:prijmeni>SCHWARZENBERG</are:prijmeni>
    </are:fosoba>
   </are:Clen>
   <are:Clen dza="2015-07-16">
    <are:fosoba>
     <are:adresa>
      <are:ruianKod>21714649</are:ruianKod>
      <are:stat>203</are:stat>
      <are:psc>11000</are:psc>
      <are:okres>Hlavní město Praha</are:okres>
      <are:obec>Praha</are:obec>
      <are:castObce>Nové Město</are:castObce>
      <are:mop>Praha 1</are:mop>
      <are:ulice>Klimentská</are:ulice>
      <are:cisloPop>2065</are:cisloPop>
      <are:cisloOr>17</are:cisloOr>
     </are:adresa>
     <are:jmeno>JIŘINA</are:jmeno>
     <are:prijmeni>ŠIKLOVÁ</are:prijmeni>
     <are:titulPred>Doc.PhDr.</are:titulPred>
    </are:fosoba>
   </are:Clen>
  </are:Jiny_organ>
 </are:Vypis_VREO>
</are:Odpoved>
</are:Ares_odpovedi>
