<?xml version="1.0" encoding="UTF-8"?>
<are:Ares_odpovedi xmlns:are="http://wwwinfo.mfcr.cz/ares/xml_doc/schemas/ares/ares_answer_vreo/v_1.0.0" 
odpoved_datum_cas="2019-01-07T10:00:47"
odpoved_pocet="1" odpoved_typ="Vypis_VREO" vystup_format="XML" xslt="klient" validation_XSLT="http://wwwinfo.mfcr.cz/ares/xml_doc/schemas/ares/ares_odpovedi.xsl" xmlns:xsi="http://www.w3.org/2001/XMLSchema-instance" xsi:schemaLocation="http://wwwinfo.mfcr.cz/ares/xml_doc/schemas/ares/ares_answer_vreo/v_1.0.0 ../ares_answer_vreo.xsd" Id="aresds">
<are:Odpoved>
 <are:Pomocne_ID>0</are:Pomocne_ID>
 <are:Vysledek_hledani>
  <are:Kod>1</are:Kod>
 </are:Vysledek_hledani>
 <are:Pocet_zaznamu>1</are:Pocet_zaznamu>
 <are:Vypis_VREO>
  <are:Uvod>
   <are:Nadpis>Výpis z veřejného rejstříku v ARES - elektronický opis</are:Nadpis>
   <are:Aktualizace_DB>2019-01-07</are:Aktualizace_DB>
   <are:Datum_vypisu>2019-01-07</are:Datum_vypisu>
   <are:Cas_vypisu>10:00:47</are:Cas_vypisu>
   <are:Typ_vypisu>aktualni</are:Typ_vypisu>
  </are:Uvod>
  <are:Zakladni_udaje>
   <are:Rejstrik>RSVJ</are:Rejstrik>
   <are:ICO>26835916</are:ICO>
   <are:ObchodniFirma>Společenství vlastníků domu Pionýrů 828/2</are:ObchodniFirma>
   <are:Sidlo>
    <are:ruianKod>3291596</are:ruianKod>
    <are:stat>203</are:stat>
    <are:psc>70800</are:psc>
    <are:obec>Ostrava</are:obec>
    <are:castObce>Poruba</are:castObce>
    <are:ulice>Pionýrů</are:ulice>
    <are:cisloPop>828</are:cisloPop>
    <are:cisloOr>2</are:cisloOr>
   </are:Sidlo>
   <are:DatumVzniku>2004-03-01</are:DatumVzniku>
   <are:DatumZapisu>2004-06-24</are:DatumZapisu>
   <are:Cinnosti>
    <are:Ucel>
     <are:Text>
Zajišťování správy domu a pozemku
     </are:Text>
    </are:Ucel>
   </are:Cinnosti>
  </are:Zakladni_udaje>
  <are:Statutarni_organ dza="2004-06-24">
   <are:Nazev>Statutární orgán</are:Nazev>
   <are:ZpusobJednani dza="2016-04-27">
    <are:Text>
Předseda jedná za výbor navenek. Jde-li o písemný právní úkon, musí být podepsán alespoň dvěma členy výboru.
    </are:Text>
   </are:ZpusobJednani>
   <are:Clen dza="2004-06-24" dvy="2008-07-29">
    <are:funkce>
     <are:nazev>člen výboru</are:nazev>
    </are:funkce>
    <are:fosoba>
     <are:adresa>
      <are:ruianKod>3291596</are:ruianKod>
      <are:stat>203</are:stat>
      <are:obec>Ostrava</are:obec>
      <are:castObce>Poruba</are:castObce>
      <are:ulice>Pionýrů</are:ulice>
      <are:cisloTxt>828/2</are:cisloTxt>
     </are:adresa>
     <are:jmeno>Josef</are:jmeno>
     <are:prijmeni>Řezníček</are:prijmeni>
    </are:fosoba>
   </are:Clen>
   <are:Clen dza="2004-06-24" dvy="2013-12-04">
    <are:funkce>
     <are:nazev>předseda výboru</are:nazev>
    </are:funkce>
    <are:fosoba>
     <are:adresa>
      <are:ruianKod>3291596</are:ruianKod>
      <are:stat>203</are:stat>
      <are:obec>Ostrava</are:obec>
      <are:castObce>Poruba</are:castObce>
      <are:ulice>Pionýrů</are:ulice>
      <are:cisloTxt>828/2</are:cisloTxt>
     </are:adresa>
     <are:jmeno>Jiří</are:jmeno>
     <are:prijmeni>Němec</are:prijmeni>
     <are:titulPred>Ing.</are:titulPred>
    </are:fosoba>
   </are:Clen>
   <are:Clen dza="2004-06-24" dvy="2013-12-28">
    <are:funkce>
     <are:nazev>člen výboru</are:nazev>
    </are:funkce>
    <are:fosoba>
     <are:adresa>
      <are:ruianKod>3291596</are:ruianKod>
      <are:stat>203</are:stat>
      <are:obec>Ostrava</are:obec>
      <are:castObce>Poruba</are:castObce>
      <are:ulice>Pionýrů</are:ulice>
      <are:cisloTxt>828/2</are:cisloTxt>
     </are:adresa>
     <are:jmeno>Stanislav</are:jmeno>
     <are:prijmeni>Hranický</are:prijmeni>
    </are:fosoba>
   </are:Clen>
   <are:Clen dza="2008-07-29" dvy="2013-12-04">
    <are:funkce>
     <are:nazev>člen výboru</are:nazev>
    </are:funkce>
    <are:fosoba>
     <are:adresa>
      <are:ruianKod>3291596</are:ruianKod>
      <are:stat>203</are:stat>
      <are:psc>70800</are:psc>
      <are:obec>Ostrava</are:obec>
      <are:castObce>Poruba</are:castObce>
      <are:ulice>Pionýrů</are:ulice>
      <are:cisloTxt>828/2</are:cisloTxt>
     </are:adresa>
     <are:jmeno>Aleš</are:jmeno>
     <are:prijmeni>Kubica</are:prijmeni>
    </are:fosoba>
   </are:Clen>
   <are:Clen dza="2013-12-04" dvy="2016-04-27">
    <are:clenstvi>
     <are:zanikClenstvi>2009-03-04</are:zanikClenstvi>
    </are:clenstvi>
    <are:funkce>
     <are:nazev>předseda výboru</are:nazev>
     <are:zanikFunkce>2009-03-04</are:zanikFunkce>
    </are:funkce>
    <are:fosoba>
     <are:adresa>
      <are:ruianKod>3291596</are:ruianKod>
      <are:stat>203</are:stat>
      <are:psc>70800</are:psc>
      <are:obec>Ostrava</are:obec>
      <are:castObce>Poruba</are:castObce>
      <are:ulice>Pionýrů</are:ulice>
      <are:cisloPop>828</are:cisloPop>
      <are:cisloOr>2</are:cisloOr>
     </are:adresa>
     <are:jmeno>JIŘÍ</are:jmeno>
     <are:prijmeni>NĚMEC</are:prijmeni>
    </are:fosoba>
   </are:Clen>
   <are:Clen dza="2013-12-04" dvy="2016-04-27">
    <are:clenstvi>
     <are:zanikClenstvi>2013-06-09</are:zanikClenstvi>
    </are:clenstvi>
    <are:funkce>
     <are:nazev>člen výboru</are:nazev>
    </are:funkce>
    <are:fosoba>
     <are:adresa>
      <are:ruianKod>3291596</are:ruianKod>
      <are:stat>203</are:stat>
      <are:psc>70800</are:psc>
      <are:obec>Ostrava</are:obec>
      <are:castObce>Poruba</are:castObce>
      <are:ulice>Pionýrů</are:ulice>
      <are:cisloPop>828</are:cisloPop>
      <are:cisloOr>2</are:cisloOr>
     </are:adresa>
     <are:jmeno>ALEŠ</are:jmeno>
     <are:prijmeni>KUBICA</are:prijmeni>
    </are:fosoba>
   </are:Clen>
   <are:Clen dza="2013-12-28" dvy="2016-04-27">
    <are:clenstvi>
     <are:vznikClenstvi>2013-10-24</are:vznikClenstvi>
     <are:zanikClenstvi>2015-11-03</are:zanikClenstvi>
    </are:clenstvi>
    <are:funkce>
     <are:nazev>člen výboru</are:nazev>
    </are:funkce>
    <are:fosoba>
     <are:adresa>
      <are:ruianKod>3291596</are:ruianKod>
      <are:stat>203</are:stat>
      <are:psc>70800</are:psc>
      <are:obec>Ostrava</are:obec>
      <are:castObce>Poruba</are:castObce>
      <are:ulice>Pionýrů</are:ulice>
      <are:cisloPop>828</are:cisloPop>
      <are:cisloOr>2</are:cisloOr>
     </are:adresa>
     <are:jmeno>LENKA</are:jmeno>
     <are:prijmeni>CHARVÁTKOVÁ</are:prijmeni>
    </are:fosoba>
   </are:Clen>
   <are:Clen dza="2016-04-27" dvy="2016-10-05">
    <are:clenstvi>
     <are:vznikClenstvi>2015-11-03</are:vznikClenstvi>
    </are:clenstvi>
    <are:funkce>
     <are:nazev>člen výboru</are:nazev>
    </are:funkce>
    <are:fosoba>
     <are:adresa>
      <are:ruianKod>3291596</are:ruianKod>
      <are:stat>203</are:stat>
      <are:psc>70800</are:psc>
      <are:okres>Ostrava-město</are:okres>
      <are:obec>Ostrava</are:obec>
      <are:castObce>Poruba</are:castObce>
      <are:ulice>Pionýrů</are:ulice>
      <are:cisloPop>828</are:cisloPop>
      <are:cisloOr>2</are:cisloOr>
     </are:adresa>
     <are:jmeno>LENKA</are:jmeno>
     <are:prijmeni>CHARVÁTKOVÁ</are:prijmeni>
    </are:fosoba>
   </are:Clen>
   <are:Clen dza="2016-04-27" dvy="2018-12-29">
    <are:clenstvi>
     <are:vznikClenstvi>2015-11-03</are:vznikClenstvi>
     <are:zanikClenstvi>2018-10-31</are:zanikClenstvi>
    </are:clenstvi>
    <are:funkce>
     <are:nazev>předseda výboru</are:nazev>
     <are:vznikFunkce>2015-11-03</are:vznikFunkce>
     <are:zanikFunkce>2018-10-31</are:zanikFunkce>
    </are:funkce>
    <are:fosoba>
     <are:adresa>
      <are:ruianKod>3291596</are:ruianKod>
      <are:stat>203</are:stat>
      <are:psc>70800</are:psc>
      <are:okres>Ostrava-město</are:okres>
      <are:obec>Ostrava</are:obec>
      <are:castObce>Poruba</are:castObce>
      <are:ulice>Pionýrů</are:ulice>
      <are:cisloPop>828</are:cisloPop>
      <are:cisloOr>2</are:cisloOr>
     </are:adresa>
     <are:jmeno>JIŘÍ</are:jmeno>
     <are:prijmeni>NĚMEC</are:prijmeni>
     <are:titulPred>Ing.</are:titulPred>
    </are:fosoba>
   </are:Clen>
   <are:Clen dza="2016-04-27" dvy="2018-12-29">
    <are:clenstvi>
     <are:vznikClenstvi>2015-11-03</are:vznikClenstvi>
     <are:zanikClenstvi>2018-10-21</are:zanikClenstvi>
    </are:clenstvi>
    <are:funkce>
     <are:nazev>člen výboru</are:nazev>
    </are:funkce>
    <are:fosoba>
     <are:adresa>
      <are:ruianKod>3291596</are:ruianKod>
      <are:stat>203</are:stat>
      <are:psc>70800</are:psc>
      <are:okres>Ostrava-město</are:okres>
      <are:obec>Ostrava</are:obec>
      <are:castObce>Poruba</are:castObce>
      <are:ulice>Pionýrů</are:ulice>
      <are:cisloPop>828</are:cisloPop>
      <are:cisloOr>2</are:cisloOr>
     </are:adresa>
     <are:jmeno>ALEŠ</are:jmeno>
     <are:prijmeni>KUBICA</are:prijmeni>
    </are:fosoba>
   </are:Clen>
   <are:Clen dza="2016-10-05" dvy="2018-12-29">
    <are:clenstvi>
     <are:vznikClenstvi>2015-11-03</are:vznikClenstvi>
     <are:zanikClenstvi>2018-10-21</are:zanikClenstvi>
    </are:clenstvi>
    <are:funkce>
     <are:nazev>člen výboru</are:nazev>
    </are:funkce>
    <are:fosoba>
     <are:adresa>
      <are:ruianKod>3291596</are:ruianKod>
      <are:stat>203</are:stat>
      <are:psc>70800</are:psc>
      <are:okres>Ostrava-město</are:okres>
      <are:obec>Ostrava</are:obec>
      <are:castObce>Poruba</are:castObce>
      <are:ulice>Pionýrů</are:ulice>
      <are:cisloPop>828</are:cisloPop>
      <are:cisloOr>2</are:cisloOr>
     </are:adresa>
     <are:jmeno>LENKA</are:jmeno>
     <are:prijmeni>SLAVÍKOVÁ</are:prijmeni>
    </are:fosoba>
   </are:Clen>
   <are:Clen dza="2018-12-29">
    <are:clenstvi>
     <are:vznikClenstvi>2018-10-31</are:vznikClenstvi>
    </are:clenstvi>
    <are:funkce>
     <are:nazev>předseda výboru</are:nazev>
     <are:vznikFunkce>2018-10-31</are:vznikFunkce>
    </are:funkce>
    <are:fosoba>
     <are:adresa>
      <are:ruianKod>3290778</are:ruianKod>
      <are:stat>203</are:stat>
      <are:psc>70800</are:psc>
      <are:okres>Ostrava-město</are:okres>
      <are:obec>Ostrava</are:obec>
      <are:castObce>Poruba</are:castObce>
      <are:ulice>17. listopadu</are:ulice>
      <are:cisloPop>749</are:cisloPop>
      <are:cisloOr>58</are:cisloOr>
     </are:adresa>
     <are:jmeno>ROSTISLAV</are:jmeno>
     <are:prijmeni>PANTŮČEK</are:prijmeni>
    </are:fosoba>
   </are:Clen>
   <are:Clen dza="2018-12-29">
    <are:clenstvi>
     <are:vznikClenstvi>2018-10-31</are:vznikClenstvi>
    </are:clenstvi>
    <are:funkce>
     <are:nazev>člen výboru</are:nazev>
    </are:funkce>
    <are:fosoba>
     <are:adresa>
      <are:ruianKod>3291596</are:ruianKod>
      <are:stat>203</are:stat>
      <are:psc>70800</are:psc>
      <are:okres>Ostrava-město</are:okres>
      <are:obec>Ostrava</are:obec>
      <are:castObce>Poruba</are:castObce>
      <are:ulice>Pionýrů</are:ulice>
      <are:cisloPop>828</are:cisloPop>
      <are:cisloOr>2</are:cisloOr>
     </are:adresa>
     <are:jmeno>ZDEŇKA</are:jmeno>
     <are:prijmeni>KUBOŠOVÁ</are:prijmeni>
     <are:titulPred>Ing.</are:titulPred>
    </are:fosoba>
   </are:Clen>
   <are:Clen dza="2018-12-29">
    <are:clenstvi>
     <are:vznikClenstvi>2018-10-31</are:vznikClenstvi>
    </are:clenstvi>
    <are:funkce>
     <are:nazev>člen výboru</are:nazev>
    </are:funkce>
    <are:fosoba>
     <are:adresa>
      <are:ruianKod>3296997</are:ruianKod>
      <are:stat>203</are:stat>
      <are:psc>70800</are:psc>
      <are:okres>Ostrava-město</are:okres>
      <are:obec>Ostrava</are:obec>
      <are:castObce>Poruba</are:castObce>
      <are:ulice>Karla Pokorného</are:ulice>
      <are:cisloPop>1363</are:cisloPop>
      <are:cisloOr>53</are:cisloOr>
     </are:adresa>
     <are:jmeno>RADEK</are:jmeno>
     <are:prijmeni>HOFÍREK</are:prijmeni>
     <are:titulPred>Bc.</are:titulPred>
    </are:fosoba>
   </are:Clen>
  </are:Statutarni_organ>
 </are:Vypis_VREO>
</are:Odpoved>
</are:Ares_odpovedi>
