<?xml version="1.0" encoding="UTF-8"?>
<are:Ares_odpovedi xmlns:are="http://wwwinfo.mfcr.cz/ares/xml_doc/schemas/ares/ares_answer_vreo/v_1.0.0" 
odpoved_datum_cas="2018-02-08T14:49:04"
odpoved_pocet="1" odpoved_typ="Vypis_VREO" vystup_format="XML" xslt="klient" validation_XSLT="http://wwwinfo.mfcr.cz/ares/xml_doc/schemas/ares/ares_odpovedi.xsl" xmlns:xsi="http://www.w3.org/2001/XMLSchema-instance" xsi:schemaLocation="http://wwwinfo.mfcr.cz/ares/xml_doc/schemas/ares/ares_answer_vreo/v_1.0.0 ../ares_answer_vreo.xsd" Id="aresds">
<are:Odpoved>
 <are:Pomocne_ID>0</are:Pomocne_ID>
 <are:Vysledek_hledani>
  <are:Kod>1</are:Kod>
 </are:Vysledek_hledani>
 <are:Pocet_zaznamu>1</are:Pocet_zaznamu>
 <are:Vypis_VREO>
  <are:Uvod>
   <are:Nadpis>Výpis z veřejného rejstříku v ARES - elektronický opis</are:Nadpis>
   <are:Aktualizace_DB>2018-02-08</are:Aktualizace_DB>
   <are:Datum_vypisu>2018-02-08</are:Datum_vypisu>
   <are:Cas_vypisu>14:49:04</are:Cas_vypisu>
   <are:Typ_vypisu>aktualni</are:Typ_vypisu>
  </are:Uvod>
  <are:Zakladni_udaje>
   <are:Rejstrik>OR</are:Rejstrik>
   <are:ICO>61329363</are:ICO>
   <are:ObchodniFirma>SUPLES s.r.o.</are:ObchodniFirma>
   <are:Sidlo>
    <are:ruianKod>23522186</are:ruianKod>
    <are:stat>203</are:stat>
    <are:psc>43001</are:psc>
    <are:okres>Chomutov</are:okres>
    <are:obec>Chomutov</are:obec>
    <are:ulice>Dostojevského</are:ulice>
    <are:cisloTxt>4155</are:cisloTxt>
   </are:Sidlo>
   <are:DatumZapisu>1994-08-26</are:DatumZapisu>
   <are:DatumVymazu>2018-01-31</are:DatumVymazu>
   <are:DuvodVymazu>
    <are:Text>
Vymazává se společnost SUPLES s.r.o., se sídlem Chomutov, Dostojevského 4155, PSČ 43001, identifikační číslo : 613 29 363 ke dni právní moci tohoto usnesení, včetně všech zapsaných skutečností.
    </are:Text>
    <are:Text>
Právní důvod výmazu : Společnost byla vymazána na základě usnesení Krajského soudu v Ústí nad Labem ze dne 26.5.2008, č.j. 69 K 5/2006-111, kterým byl zrušen konkurs na majetek úpadce  SUPLES s.r.o. se sídlem  Chomutov, Dostojevského 4155, PSČ 430 01, IČ
613 29 363 z důvodu splnění rozvrhového usnesení. Usnesení v tomto výroku nabylo právní moci dne 24.6.2008.
    </are:Text>
   </are:DuvodVymazu>
   <are:Cinnosti>
    <are:PredmetPodnikani>
     <are:Text>
zprostředkování obchodní činnosti
     </are:Text>
     <are:Text>
koupě zboží za účelem jeho dalšího prodeje a prodej
     </are:Text>
     <are:Text>
malířské a natěračské práce
     </are:Text>
     <are:Text>
zednictví
     </are:Text>
     <are:Text>
truhlářství
     </are:Text>
    </are:PredmetPodnikani>
   </are:Cinnosti>
  </are:Zakladni_udaje>
  <are:Statutarni_organ dza="1994-08-26" dvy="2018-01-31">
   <are:Nazev>Statutární orgán</are:Nazev>
   <are:ZpusobJednani dza="1994-08-26" dvy="2018-01-31">
    <are:Text>
Jednatel jedná jménem společnosti navenek a podepisuje tak,
že k obchodnímu jménu společnosti připojí svůj podpis.
    </are:Text>
   </are:ZpusobJednani>
   <are:Clen dza="1994-08-26" dvy="1996-03-08">
    <are:funkce>
     <are:nazev>Jednatel</are:nazev>
    </are:funkce>
    <are:fosoba>
     <are:adresa>
      <are:ruianKod>23519631</are:ruianKod>
      <are:stat>203</are:stat>
      <are:obec>Chomutov</are:obec>
      <are:ulice>Sluneční</are:ulice>
      <are:cisloTxt>3899</are:cisloTxt>
     </are:adresa>
     <are:jmeno>Olga</are:jmeno>
     <are:prijmeni>Berezňáková</are:prijmeni>
    </are:fosoba>
   </are:Clen>
   <are:Clen dza="1996-03-08" dvy="1997-11-03">
    <are:funkce>
     <are:nazev>Jednatel</are:nazev>
    </are:funkce>
    <are:fosoba>
     <are:adresa>
      <are:ruianKod>23519631</are:ruianKod>
      <are:stat>203</are:stat>
      <are:obec>Chomutov</are:obec>
      <are:ulice>Sluneční</are:ulice>
      <are:cisloTxt>3899</are:cisloTxt>
     </are:adresa>
     <are:prijmeni>Olga Petrovna Bereznjak</are:prijmeni>
    </are:fosoba>
   </are:Clen>
   <are:Clen dza="1997-11-03" dvy="2000-02-16">
    <are:funkce>
     <are:nazev>Jednatel</are:nazev>
    </are:funkce>
    <are:fosoba>
     <are:adresa>
      <are:stat>203</are:stat>
      <are:text>Spartakovskaja 16A kv. 20, CHIMKI Moskva, Ruská federace         v ČR: Chomutov, Sluneční 3899</are:text>
     </are:adresa>
     <are:jmeno>Olga</are:jmeno>
     <are:prijmeni>Berezniak</are:prijmeni>
    </are:fosoba>
   </are:Clen>
   <are:Clen dza="2000-02-16" dvy="2002-12-04">
    <are:funkce>
     <are:nazev>Jednatel</are:nazev>
     <are:zanikFunkce>2002-07-24</are:zanikFunkce>
    </are:funkce>
    <are:fosoba>
     <are:adresa>
      <are:stat>203</are:stat>
      <are:text>Spartakovskaja 16A kv. 20, CHIMKI Moskva, Ruská federace         v ČR: Chomutov, Sluneční 3899</are:text>
     </are:adresa>
     <are:jmeno>Olga</are:jmeno>
     <are:prijmeni>Bereznyak</are:prijmeni>
     <are:titulPred>Mgr.</are:titulPred>
    </are:fosoba>
   </are:Clen>
   <are:Clen dza="2002-12-04" dvy="2018-01-31">
    <are:funkce>
     <are:nazev>Jednatel</are:nazev>
     <are:vznikFunkce>2002-07-24</are:vznikFunkce>
    </are:funkce>
    <are:fosoba>
     <are:adresa>
      <are:stat>203</are:stat>
      <are:text>Spartakovskaja 16A kv. 20, CHIMKI Moskva, Ruská federace, v ČR: Chomutov, Sluneční 3899</are:text>
     </are:adresa>
     <are:jmeno>Vladimir</are:jmeno>
     <are:prijmeni>Bereznyak</are:prijmeni>
    </are:fosoba>
   </are:Clen>
  </are:Statutarni_organ>
  <are:Jiny_organ dza="1994-08-26" dvy="2018-01-31">
   <are:Nazev>Společníci</are:Nazev>
   <are:Clen dza="2002-12-04" dvy="2018-01-31">
    <are:fosoba>
     <are:adresa>
      <are:stat>203</are:stat>
      <are:text>Červených partyzánů 61-43, Usole-Sibirskoe 665470, Irkutskaja oblast, Ruská federace, v ČR: Chomutov, Pod Břízami 5233</are:text>
     </are:adresa>
     <are:jmeno>Anatoli</are:jmeno>
     <are:prijmeni>Moskvitine</are:prijmeni>
    </are:fosoba>
   </are:Clen>
   <are:Clen dza="2002-12-04" dvy="2018-01-31">
    <are:fosoba>
     <are:adresa>
      <are:stat>203</are:stat>
      <are:text>Spartakovskaja 16A kv. 20, CHIMKI Moskva, Ruská federace       v ČR: Chomutov, Sluneční 3899</are:text>
     </are:adresa>
     <are:jmeno>Vladimir</are:jmeno>
     <are:prijmeni>Bereznyak</are:prijmeni>
    </are:fosoba>
   </are:Clen>
  </are:Jiny_organ>
 </are:Vypis_VREO>
</are:Odpoved>
</are:Ares_odpovedi>
