<?xml version="1.0" encoding="UTF-8"?>
<are:Ares_odpovedi xmlns:are="http://wwwinfo.mfcr.cz/ares/xml_doc/schemas/ares/ares_answer_vreo/v_1.0.0" 
odpoved_datum_cas="2017-12-17T05:38:10"
odpoved_pocet="1" odpoved_typ="Vypis_VREO" vystup_format="XML" xslt="klient" validation_XSLT="http://wwwinfo.mfcr.cz/ares/xml_doc/schemas/ares/ares_odpovedi.xsl" xmlns:xsi="http://www.w3.org/2001/XMLSchema-instance" xsi:schemaLocation="http://wwwinfo.mfcr.cz/ares/xml_doc/schemas/ares/ares_answer_vreo/v_1.0.0 ../ares_answer_vreo.xsd" Id="aresds">
<are:Odpoved>
 <are:Pomocne_ID>0</are:Pomocne_ID>
 <are:Vysledek_hledani>
  <are:Kod>1</are:Kod>
 </are:Vysledek_hledani>
 <are:Pocet_zaznamu>1</are:Pocet_zaznamu>
 <are:Vypis_VREO>
  <are:Uvod>
   <are:Nadpis>Výpis z veřejného rejstříku v ARES - elektronický opis</are:Nadpis>
   <are:Aktualizace_DB>2017-12-09</are:Aktualizace_DB>
   <are:Datum_vypisu>2017-12-17</are:Datum_vypisu>
   <are:Cas_vypisu>05:38:10</are:Cas_vypisu>
   <are:Typ_vypisu>aktualni</are:Typ_vypisu>
  </are:Uvod>
  <are:Zakladni_udaje>
   <are:Rejstrik>OR</are:Rejstrik>
   <are:ICO>63079399</are:ICO>
   <are:ObchodniFirma>NiKO a.s.</are:ObchodniFirma>
   <are:Sidlo>
    <are:ruianKod>21951551</are:ruianKod>
    <are:stat>203</are:stat>
    <are:obec>Praha 4</are:obec>
    <are:ulice>Bartoškova</are:ulice>
    <are:cisloTxt>2</are:cisloTxt>
   </are:Sidlo>
   <are:DatumZapisu>1995-05-30</are:DatumZapisu>
   <are:DatumVymazu>2016-09-27</are:DatumVymazu>
   <are:DuvodVymazu>
    <are:Text>
Společnost NiKO a.s., Praha 4, Bartoškova 2, identifikační číslo 630 79 399. Právním důvodem je zrušení konkursu na majetek úpadce, jelikož majetek podstaty nepostačuje k úhradě nákladů konkursu, a to Usnesením Městského soudu v Praze ze dne 16.03.2006 č.
j. 99 K 75/2000 - 125, které nabylo právní moci dne 19.04.2006 výrok I. a dne
23.03.2006 výrok II.
    </are:Text>
   </are:DuvodVymazu>
  </are:Zakladni_udaje>
  <are:Statutarni_organ dza="1995-05-30" dvy="2016-09-27">
   <are:Nazev>Statutární orgán - představenstvo</are:Nazev>
   <are:ZpusobJednani dza="1995-05-30" dvy="2016-09-27">
    <are:Text>
1. Společnost zastupuje předseda představenstva samostatně nebo
místopředseda představenstva společně s jedním členem představe-
nstva.
2. Za společnost podepisuje předseda představenstva nebo místo-
předseda společně s jedním členem představenstva.
Všichni tak činí tím způsobem, že k vytištěnému nebo nadepsanému
názvu společnosti či otisku razítka společnosti připojí svůj
podpis.
    </are:Text>
   </are:ZpusobJednani>
   <are:Clen dza="1995-05-30" dvy="2013-08-31">
    <are:funkce>
     <are:nazev>Předseda představenstva</are:nazev>
    </are:funkce>
    <are:fosoba>
     <are:adresa>
      <are:stat>203</are:stat>
      <are:obec>Praha 4</are:obec>
      <are:ulice>Mayerského</are:ulice>
      <are:cisloTxt>2049</are:cisloTxt>
     </are:adresa>
     <are:jmeno>Ivan</are:jmeno>
     <are:prijmeni>Svoboda</are:prijmeni>
     <are:titulPred>1.ing.</are:titulPred>
    </are:fosoba>
   </are:Clen>
   <are:Clen dza="1995-05-30" dvy="2016-09-27">
    <are:funkce>
     <are:nazev>místopředseda představenstva</are:nazev>
    </are:funkce>
    <are:fosoba>
     <are:adresa>
      <are:ruianKod>21954488</are:ruianKod>
      <are:stat>203</are:stat>
      <are:obec>Praha 4</are:obec>
      <are:ulice>U Děkanky</are:ulice>
      <are:cisloTxt>2</are:cisloTxt>
     </are:adresa>
     <are:prijmeni>2. Dana Čechová</are:prijmeni>
    </are:fosoba>
   </are:Clen>
   <are:Clen dza="1995-05-30" dvy="2016-09-27">
    <are:funkce>
     <are:nazev>člen představenstva</are:nazev>
    </are:funkce>
    <are:fosoba>
     <are:adresa>
      <are:ruianKod>22178481</are:ruianKod>
      <are:stat>203</are:stat>
      <are:obec>Praha 6</are:obec>
      <are:ulice>Jaselská</are:ulice>
      <are:cisloTxt>38</are:cisloTxt>
     </are:adresa>
     <are:jmeno>Stanislav</are:jmeno>
     <are:prijmeni>Chmura</are:prijmeni>
     <are:titulPred>3.JUDr.</are:titulPred>
    </are:fosoba>
   </are:Clen>
   <are:Clen dza="2013-08-31" dvy="2013-10-15">
    <are:funkce>
     <are:nazev>Předseda představenstva</are:nazev>
    </are:funkce>
    <are:fosoba>
     <are:adresa>
      <are:ruianKod>21704716</are:ruianKod>
      <are:stat>203</are:stat>
      <are:psc>11000</are:psc>
      <are:obec>Praha 1</are:obec>
      <are:castObce>Nové Město</are:castObce>
      <are:ulice>Vodičkova</are:ulice>
      <are:cisloPop>681</are:cisloPop>
      <are:cisloOr>18</are:cisloOr>
     </are:adresa>
     <are:jmeno>IVAN</are:jmeno>
     <are:prijmeni>SVOBODA</are:prijmeni>
     <are:titulPred>1.ing.</are:titulPred>
    </are:fosoba>
   </are:Clen>
   <are:Clen dza="2013-10-15" dvy="2015-01-30">
    <are:funkce>
     <are:nazev>Předseda představenstva</are:nazev>
    </are:funkce>
    <are:fosoba>
     <are:adresa>
      <are:ruianKod>21720843</are:ruianKod>
      <are:stat>203</are:stat>
      <are:psc>11000</are:psc>
      <are:okres>Hlavní město Praha</are:okres>
      <are:obec>Praha</are:obec>
      <are:castObce>Staré Město</are:castObce>
      <are:mop>Praha 1</are:mop>
      <are:ulice>Michalská</are:ulice>
      <are:cisloPop>511</are:cisloPop>
      <are:cisloOr>6</are:cisloOr>
     </are:adresa>
     <are:jmeno>IVAN</are:jmeno>
     <are:prijmeni>SVOBODA</are:prijmeni>
     <are:titulPred>1.ing.</are:titulPred>
    </are:fosoba>
   </are:Clen>
  </are:Statutarni_organ>
  <are:Jiny_organ dza="1995-05-30" dvy="2016-09-27">
   <are:Nazev>Dozorčí rada</are:Nazev>
   <are:Clen dza="1995-05-30" dvy="2016-09-27">
    <are:funkce>
     <are:nazev>předseda</are:nazev>
    </are:funkce>
    <are:fosoba>
     <are:adresa>
      <are:ruianKod>22425586</are:ruianKod>
      <are:stat>203</are:stat>
      <are:obec>Praha 9</are:obec>
      <are:ulice>Kbelská</are:ulice>
      <are:cisloTxt>622/11</are:cisloTxt>
     </are:adresa>
     <are:jmeno>Helena</are:jmeno>
     <are:prijmeni>Žáková</are:prijmeni>
    </are:fosoba>
   </are:Clen>
   <are:Clen dza="1995-05-30" dvy="2016-09-27">
    <are:funkce>
     <are:nazev>člen</are:nazev>
    </are:funkce>
    <are:fosoba>
     <are:adresa>
      <are:ruianKod>22347658</are:ruianKod>
      <are:stat>203</are:stat>
      <are:obec>Praha 8</are:obec>
      <are:ulice>Hřenská</are:ulice>
      <are:cisloTxt>3</are:cisloTxt>
     </are:adresa>
     <are:jmeno>Pavel</are:jmeno>
     <are:prijmeni>Procházka</are:prijmeni>
    </are:fosoba>
   </are:Clen>
  </are:Jiny_organ>
 </are:Vypis_VREO>
</are:Odpoved>
</are:Ares_odpovedi>
